<?xml version="1.0" encoding="UTF-8"?>
<Game-List>
	<Game id="RMCEZH" en="ZPL's Hide and Seek Collection" zhcn="ZPL's Hide and Seek Collection"/>
	<Game id="RMCEZ2" en="ZPL's Track Collection" zhcn="ZPL's Track Collection"/>
	<Game id="RTZK08" en="Zack &amp; Wiki - Barbarosui Bomul" zhcn="宝岛Z 巴尔巴罗斯的秘宝(韩)"/>
	<Game id="RTZE08" en="Zack &amp; Wiki: Quest for Barbaros' Treasure" zhcn="宝岛Z 巴尔巴罗斯的秘宝(美)" collection="Z"/>
	<Game id="RTZP08" en="Zack &amp; Wiki: Quest for Barbaros' Treasure" zhcn="宝岛Z 巴尔巴罗斯的秘宝(欧)"/>
	<Game id="RKNJ2N" en="Zaidan Houjin Nihon Kanji Nouryoku Kentei Kyoukai Kounin: Kanken Wii: Kanji-ou Ketteisen" zhcn="汉检Wii 汉字王决定战(日)"/>
	<Game id="RKJJ0Q" en="Zaidan Houjin Nihon Kanji Nouryoku Kentei Kyoukai Koushiki Soft: 250 Mannin no Kanken: Wii de Tokoton Kanji Nou" zhcn="汉字能力检定协会 250万人的汉检(日)"/>
	<Game id="RZNJ01" en="Zangeki no Reginleiv" zhcn="斩击的女武神(日)"/>
	<Game id="RZNE01" en="Zangeki no Reginleiv [Eng]" zhcn="Zangeki no Reginleiv [Eng]"/>
	<Game id="GZBEB2" en="Zatch Bell! Go! Go! Mamodo Fight!!" zhcn="Zatch Bell! Go! Go! Mamodo Fight!!"/>
	<Game id="RMCEZ8" en="Zef Kart Wii" zhcn="Zef Kart Wii"/>
	<Game id="RMCEZC" en="Zef's CT Pack" zhcn="Zef's CT Pack"/>
	<Game id="GZLK01" en="Zelda no Densetsu: Kaze no Takuto" zhcn="Zelda no Densetsu: Kaze no Takuto"/>
	<Game id="SOUJ01" en="Zelda no Densetsu: Skyward Sword" zhcn="塞尔达传说 天空之剑(日或中)" collection="加速器游戏"/>
	<Game id="RZDJ01" en="Zelda no Densetsu: Twilight Princess" zhcn="塞尔达传说 黄昏公主(日或中)" collection="中文游戏"/>
	<Game id="GZ2K01" en="Zelda no Densetsu: Twilight Princess" zhcn="Zelda no Densetsu: Twilight Princess"/>
	<Game id="RDEJ0A" en="Zenkoku Dekotora Matsuri" zhcn="全日本货柜车祭典(日)"/>
	<Game id="SL2J01" en="Zero: Shinku no Chou" zhcn="零 真红之蝶(日或中)" collection="中文游戏"/>
	<Game id="R4ZJ01" en="Zero: Tsukihami no Kamen" zhcn="零 月蚀之假面(日或中)" collection="中文游戏"/>
	<Game id="S2ZE52" en="Zhu Zhu Pets: Featuring The Wild Bunch" zhcn="开心鼠园2(美)" collection="Z"/>
	<Game id="S2ZP52" en="Zhu Zhu Pets: Featuring the Wild Bunch" zhcn="开心鼠园2(欧)"/>
	<Game id="RZHX5G" en="Zoo Hospital" zhcn="动物医院[WiFi](X)"/>
	<Game id="RZHP5G" en="Zoo Hospital" zhcn="动物医院[WiFi](欧)"/>
	<Game id="RZHE5G" en="Zoo Hospital" zhcn="动物医院[WiFi](美)" collection="Z"/>
	<Game id="SZ5E5G" en="Zumba Fitness" zhcn="尊巴健身(美)"/>
	<Game id="SZ5PGT" en="Zumba Fitness" zhcn="尊巴南美拉丁舞(欧)"/>
	<Game id="SZ2E5G" en="Zumba Fitness 2" zhcn="尊巴南美拉丁舞 2(美)"/>
	<Game id="SZ2P5G" en="Zumba Fitness 2" zhcn="尊巴南美拉丁舞 2(欧)"/>
	<Game id="SZ2XGT" en="Zumba Fitness 2" zhcn="尊巴南美拉丁舞 2(欧)"/>
	<Game id="SU6P5G" en="Zumba Fitness Core" zhcn="Zumba Fitness Core"/>
	<Game id="SU6XGT" en="Zumba Fitness Core" zhcn="尊巴瘦身：核心版"/>
	<Game id="SU6E5G" en="Zumba Fitness Core" zhcn="尊巴健身 核心版(美)"/>
	<Game id="SZ3E5G" en="Zumba Fitness World Party" zhcn="尊巴健身 世界派对(美)"/>
	<Game id="SZ3PGT" en="Zumba Fitness World Party" zhcn="Zumba Fitness World Party"/>
	<Game id="S7FE5G" en="Zumba Kids" zhcn="Zumba Kids"/>
	<Game id="S7FPGT" en="Zumba Kids: The Ultimate Zumba Dance Party" zhcn="Zumba Kids: The Ultimate Zumba Dance Party"/>
</Game-List>
